snapedautility/__init__.py
snapedautility/detect_outliers.py
snapedautility/plot_corr.py
snapedautility/plot_histograms.py
snapedautility-0.1.5.dist-info/LICENSE
snapedautility-0.1.5.dist-info/WHEEL
snapedautility-0.1.5.dist-info/METADATA
snapedautility-0.1.5.dist-info/RECORD
