Metadata-Version: 2.1
Name: snapedautility
Version: 0.1.5
Summary: A package for doing great things!
License: MIT
Author: Kyle Ahn
Requires-Python: >=3.9,<4.0
Classifier: License :: OSI Approved :: MIT License
Classifier: Programming Language :: Python :: 3
Classifier: Programming Language :: Python :: 3.10
Classifier: Programming Language :: Python :: 3.9
Requires-Dist: altair (>=4.2.0,<5.0.0)
Requires-Dist: numpy (>=1.22.1,<2.0.0)
Requires-Dist: palmerpenguins (>=0.1.4,<0.2.0)
Requires-Dist: pandas (>=1.3.5,<2.0.0)
